scylla_api_client/__init__.py
scylla_api_client/__main__.py
scylla_api_client/api.py
scylla_api_client/cli.py
scylla_api_client/custom_argparser.py
scylla_api_client/rest/__init__.py
scylla_api_client/rest/scylla_rest_client.py
scylla_api_client-1.1.dist-info/LICENSE.AGPL
scylla_api_client-1.1.dist-info/METADATA
scylla_api_client-1.1.dist-info/WHEEL
scylla_api_client-1.1.dist-info/entry_points.txt
scylla_api_client-1.1.dist-info/top_level.txt
scylla_api_client-1.1.dist-info/RECORD
