Metadata-Version: 2.1
Name: scylla-api-client
Version: 1.1
Summary: Command line tool for managing Scylla database nodes
Home-page: https://github.com/scylladb/scylla-api-client
Author: ScyllaDB
License: GNU AGPL 3.0
Project-URL: Bug Reports, https://github.com/scylladb/scylla-api-client/issues
Classifier: License :: OSI Approved :: GNU Affero General Public License v3 or later (AGPLv3+)
Requires-Python: >=3.6
License-File: LICENSE.AGPL
Requires-Dist: requests
